u_world-0.0.0.dist-info/licenses/LICENSE
uworld/__init__.py
uworld/version.py
u_world-0.0.0.dist-info/METADATA
u_world-0.0.0.dist-info/WHEEL
u_world-0.0.0.dist-info/entry_points.txt
u_world-0.0.0.dist-info/top_level.txt
u_world-0.0.0.dist-info/RECORD
