Metadata-Version: 2.4
Name: u-world
Version: 0.0.0
Summary: U-World: Exploring the World with AI Agents Powered by Large Language Models
Home-page: https://github.com/wangxingjun778/u-world
Author: wangxingjun778
Author-email: wangxingjun778@163.com
License: Apache License 2.0
Keywords: Agent,LLM,World Model,Multimodal
Classifier: Development Status :: 4 - Beta
Classifier: License :: OSI Approved :: Apache Software License
Classifier: Operating System :: OS Independent
Classifier: Programming Language :: Python :: 3
Classifier: Programming Language :: Python :: 3.8
Classifier: Programming Language :: Python :: 3.9
Classifier: Programming Language :: Python :: 3.10
Classifier: Programming Language :: Python :: 3.11
Classifier: Programming Language :: Python :: 3.12
License-File: LICENSE
Requires-Dist: numpy
Dynamic: author
Dynamic: author-email
Dynamic: classifier
Dynamic: description
Dynamic: description-content-type
Dynamic: home-page
Dynamic: keywords
Dynamic: license
Dynamic: license-file
Dynamic: requires-dist
Dynamic: summary
